[
  {
    "text": "手すりの設置高さの一般的な目安として正しいものはどれか？",
    "choices": [
      "A. 床から50cm",
      "B. 床から75～85cm",
      "C. 床から100cm",
      "D. 利用者の身長と同じ高さ"
    ],
    "correct": 1,
    "explanation": "正解はBです。\n\n手すりの設置高さは、一般的に床から75～85cm程度が目安とされる。ただし、利用者の身体状況や使用目的に応じて個別に調整することが重要である。",
    "category": "住環境整備の技術 1"
  },
  {
    "text": "スロープの勾配について正しいものはどれか？",
    "choices": [
      "A. 1/8（12.5％）以下が理想",
      "B. 1/4（25％）程度が適当",
      "C. 勾配は気にしなくて良い",
      "D. 1/2（50％）以下であれば問題ない"
    ],
    "correct": 0,
    "explanation": "正解はAです。\n\n車椅子で安全に利用できるスロープの勾配は1/12（約8.3％）以下が理想的で、最大でも1/8（12.5％）以下とすることが望ましい。急な勾配は転倒や転落の危険がある。",
    "category": "住環境整備の技術 1"
  },
  {
    "text": "玄関の段差解消について最も適切な方法はどれか？",
    "choices": [
      "A. 必ずエレベーターを設置",
      "B. 段差の状況に応じてスロープ・踏み台・リフト等を選択",
      "C. 段差をそのまま残す",
      "D. 階段の段数を増やす"
    ],
    "correct": 1,
    "explanation": "正解はBです。\n\n玄関の段差解消は、段差の高さ、利用者の身体状況、敷地条件等を総合的に判断し、スロープ、踏み台、段差解消機、階段昇降機等から最適な方法を選択する。",
    "category": "住環境整備の技術 1"
  },
  {
    "text": "浴室の手すりで最も重要な設置場所はどれか？",
    "choices": [
      "A. 浴槽の縁（立座り用）と洗い場（移動用）",
      "B. 天井部分のみ",
      "C. 浴室入口のみ",
      "D. 浴槽内部のみ"
    ],
    "correct": 0,
    "explanation": "正解はAです。\n\n浴室では、浴槽への出入り時の立ち座り動作を支援する浴槽縁への縦手すりと、洗い場での移動を支援する横手すりの設置が重要である。転倒リスクが高い場所への適切な配置が必要。",
    "category": "住環境整備の技術 1"
  },
  {
    "text": "トイレの手すりの設置について正しいものはどれか？",
    "choices": [
      "A. 便座の片側にのみ設置すれば十分",
      "B. 便座の両側に設置し、立ち座りと姿勢保持を支援",
      "C. 床に設置する",
      "D. 天井から吊り下げる"
    ],
    "correct": 1,
    "explanation": "正解はBです。\n\nトイレでは、便座への立ち座り動作と座位での姿勢保持を支援するため、便座の両側に手すりを設置することが基本である。利用者の身体状況に応じて高さや位置を調整する。",
    "category": "住環境整備の技術 1"
  },
  {
    "text": "階段の手すりについて正しいものはどれか？",
    "choices": [
      "A. 片側にのみ設置すれば十分",
      "B. 両側に連続して設置することが理想",
      "C. 途中で途切れても問題ない",
      "D. 階段の中央部分のみに設置"
    ],
    "correct": 1,
    "explanation": "正解はBです。\n\n階段の手すりは、上り下りの安全性を確保するため、理想的には両側に連続して設置する。片麻痺の方でも左右どちらからでも利用でき、手すりが途切れると転倒の危険が高まる。",
    "category": "住環境整備の技術 1"
  },
  {
    "text": "床材の選択で最も重要な観点はどれか？",
    "choices": [
      "A. 価格の安さ",
      "B. 滑りにくさと清掃のしやすさ",
      "C. 見た目の美しさ",
      "D. 工事の簡便さ"
    ],
    "correct": 1,
    "explanation": "正解はBです。\n\n床材選択では、転倒防止のための滑りにくさと、衛生面を考慮した清掃のしやすさが最も重要である。特に水回りでは、濡れても滑りにくい材質を選択することが安全上不可欠である。",
    "category": "住環境整備の技術 1"
  },
  {
    "text": "ドアの改修について適切なものはどれか？",
    "choices": [
      "A. 全て引き戸に変更する",
      "B. 利用者の身体状況に応じて引き戸・開き戸を選択",
      "C. 開き戸のまま変更しない",
      "D. 全て自動ドアにする"
    ],
    "correct": 1,
    "explanation": "正解はBです。\n\nドアの改修は、利用者の握力、可動域、車椅子使用の有無等を考慮して選択する。引き戸は開閉が容易だが、開き戸も軽い力で開閉できるよう調整すれば利用可能な場合もある。",
    "category": "住環境整備の技術 1"
  },
  {
    "text": "照明の改善で重要なポイントはどれか？",
    "choices": [
      "A. 明るさのみを重視",
      "B. 明るさの確保と影の除去",
      "C. 色の美しさ",
      "D. 電気代の節約"
    ],
    "correct": 1,
    "explanation": "正解はBです。\n\n照明改善では、十分な明るさの確保とともに、段差や障害物を見えにくくする影を作らないことが重要である。特に階段や廊下では、均等な照度と影の除去が転倒予防に効果的である。",
    "category": "住環境整備の技術 1"
  },
  {
    "text": "住宅改修における建築基準法の考慮で重要なことはどれか？",
    "choices": [
      "A. 建築基準法は住宅改修には無関係",
      "B. 構造の安全性と法的基準の遵守",
      "C. 費用削減を最優先",
      "D. 工期短縮を最優先"
    ],
    "correct": 1,
    "explanation": "正解はBです。\n\n住宅改修では、建物の構造的安全性を確保し、建築基準法等の法的基準を遵守することが重要である。手すりの取り付けでも壁の構造を確認し、必要に応じて補強を行う必要がある。",
    "category": "住環境整備の技術 1"
  }
]